uniWeather/__init__.py
uniweather-0.1.0.dist-info/licenses/LICENSE
uniweather-0.1.0.dist-info/METADATA
uniweather-0.1.0.dist-info/WHEEL
uniweather-0.1.0.dist-info/top_level.txt
uniweather-0.1.0.dist-info/RECORD
